signalepy/__init__.py
signalepy-0.3.8.dist-info/LICENSE
signalepy-0.3.8.dist-info/WHEEL
signalepy-0.3.8.dist-info/METADATA
signalepy-0.3.8.dist-info/RECORD
