Metadata-Version: 2.1
Name: signalepy
Version: 0.3.8
Summary: Elegant Console Logger For Python Command Line Apps
Home-page: https://github.com/ShardulNalegave/signale.py
License: MIT
Keywords: logger,cli,elegant,command-line,colored
Author: Shardul Nalegave
Author-email: nalegaveshardul40@gmail.com
Requires-Python: >=3.0,<4.0
Classifier: License :: OSI Approved :: MIT License
Classifier: Programming Language :: Python :: 3
